flextree/__init__.py
flextree/examples.py
flextree/flextree.py
flextree/jsonui.py
flextree/test_flextree.py
flextree-0.3.2.dist-info/licenses/LICENSE
flextree-0.3.2.dist-info/METADATA
flextree-0.3.2.dist-info/WHEEL
flextree-0.3.2.dist-info/top_level.txt
flextree-0.3.2.dist-info/RECORD
