Metadata-Version: 2.4
Name: flextree
Version: 0.3.2
Summary: FlexTree - A flexible and intuitive Python library for creating and manipulating tree data structures
Home-page: https://github.com/znzhao/flextree
Author: Zhenning Zhao
Author-email: Zhenning Zhao <znzhaopersonal@gmail.com>
License: MIT
Project-URL: Homepage, https://github.com/znzhao/flextree
Project-URL: Bug Reports, https://github.com/znzhao/flextree/issues
Project-URL: Source, https://github.com/znzhao/flextree
Project-URL: Documentation, https://github.com/znzhao/flextree#readme
Keywords: tree,data-structure,node,hierarchy,graph
Classifier: Development Status :: 5 - Production/Stable
Classifier: Intended Audience :: Developers
Classifier: License :: OSI Approved :: MIT License
Classifier: Operating System :: OS Independent
Classifier: Programming Language :: Python :: 3
Classifier: Programming Language :: Python :: 3.6
Classifier: Programming Language :: Python :: 3.7
Classifier: Programming Language :: Python :: 3.8
Classifier: Programming Language :: Python :: 3.9
Classifier: Programming Language :: Python :: 3.10
Classifier: Programming Language :: Python :: 3.11
Classifier: Topic :: Software Development :: Libraries :: Python Modules
Requires-Python: >=3.6
License-File: LICENSE
Dynamic: author
Dynamic: home-page
Dynamic: license-file
Dynamic: requires-python
